[
  {
    "product_id": "PROD-000000",
    "product_name": "Upgradable background architecture Sports",
    "category": "Sports",
    "subcategory": "Sports - Gun",
    "brand": "TechCorp",
    "base_price": 732.87,
    "description": "Religious piece party population car deal. System law always imagine.",
    "is_active": false,
    "last_updated": "2025-06-21T15:15:28.372023",
    "ingestion_time": "2025-06-21T15:15:28.372023"
  },
  {
    "product_id": "PROD-000001",
    "product_name": "De-engineered grid-enabled array Electronics",
    "category": "Electronics",
    "subcategory": "Electronics - Large",
    "brand": "TechCorp",
    "base_price": 217.89,
    "description": "When threat receive sort. Thing rather movie natural white. Thing political oil.",
    "is_active": true,
    "last_updated": "2025-06-21T15:15:28.372023",
    "ingestion_time": "2025-06-21T15:15:28.372023"
  },
  {
    "product_id": "PROD-000002",
    "product_name": "Front-line zero tolerance strategy Books",
    "category": "Books",
    "subcategory": "Books - Must",
    "brand": "StyleMax",
    "base_price": 381.5,
    "description": "The loss account the north.\nSoldier politics modern parent through compare quality. Describe husband plant usually middle control. Ready we television ever.",
    "is_active": false,
    "last_updated": "2025-06-21T15:15:28.372023",
    "ingestion_time": "2025-06-21T15:15:28.372023"
  },
  {
    "product_id": "PROD-000003",
    "product_name": "Proactive human-resource extranet Home & Garden",
    "category": "Home & Garden",
    "subcategory": "Home & Garden - System",
    "brand": "HomeComfort",
    "base_price": 344.46,
    "description": "Room strategy skill partner necessary with. How performance race fly including and.\nHotel side space environment election stand. Soon street region chair nor former prevent.",
    "is_active": true,
    "last_updated": "2025-06-21T15:15:28.372023",
    "ingestion_time": "2025-06-21T15:15:28.372023"
  },
  {
    "product_id": "PROD-000004",
    "product_name": "Phased background projection Electronics",
    "category": "Electronics",
    "subcategory": "Electronics - Make",
    "brand": "BookWorld",
    "base_price": 332.69,
    "description": "Certain occur simply hospital always hand. Floor will until year situation. Home top fight serious to.",
    "is_active": true,
    "last_updated": "2025-06-21T15:15:28.372023",
    "ingestion_time": "2025-06-21T15:15:28.372023"
  },
  {
    "product_id": "PROD-000005",
    "product_name": "Total asynchronous info-mediaries Clothing",
    "category": "Clothing",
    "subcategory": "Clothing - Lay",
    "brand": "StyleMax",
    "base_price": 218.41,
    "description": "Law expect get woman tree. During add suddenly pressure meeting. Mrs institution because each now since tough.",
    "is_active": true,
    "last_updated": "2025-06-21T15:15:28.372023",
    "ingestion_time": "2025-06-21T15:15:28.372023"
  },
  {
    "product_id": "PROD-000006",
    "product_name": "Programmable mission-critical knowledge user Sports",
    "category": "Sports",
    "subcategory": "Sports - Everybody",
    "brand": "StyleMax",
    "base_price": 281.03,
    "description": "Car once town your. Grow western writer out wide oil yes much. Save significant surface.\nRecord you fly many. Agent however training thank.",
    "is_active": true,
    "last_updated": "2025-06-21T15:15:28.372023",
    "ingestion_time": "2025-06-21T15:15:28.372023"
  },
  {
    "product_id": "PROD-000007",
    "product_name": "Visionary intangible productivity Books",
    "category": "Books",
    "subcategory": "Books - Beautiful",
    "brand": "StyleMax",
    "base_price": 323.71,
    "description": "Song either mother federal trial decade. Congress difficult half budget listen charge. Body live phone.\nGrow identify long customer plant together husband. Rise if federal gas hold room.",
    "is_active": true,
    "last_updated": "2025-06-21T15:15:28.372023",
    "ingestion_time": "2025-06-21T15:15:28.372023"
  },
  {
    "product_id": "PROD-000008",
    "product_name": "Multi-lateral impactful open system Home & Garden",
    "category": "Home & Garden",
    "subcategory": "Home & Garden - Learn",
    "brand": "StyleMax",
    "base_price": 945.98,
    "description": "Space south owner white. Deal plant color line local treatment. Forget people whether be PM.",
    "is_active": false,
    "last_updated": "2025-06-21T15:15:28.372023",
    "ingestion_time": "2025-06-21T15:15:28.372023"
  },
  {
    "product_id": "PROD-000009",
    "product_name": "Business-focused actuating knowledgebase Electronics",
    "category": "Electronics",
    "subcategory": "Electronics - President",
    "brand": "StyleMax",
    "base_price": 597.67,
    "description": "Song small call agency us interesting. General best medical option main break.\nCharacter also speak effort officer. Rise easy service heart tell.",
    "is_active": true,
    "last_updated": "2025-06-21T15:15:28.372023",
    "ingestion_time": "2025-06-21T15:15:28.372023"
  },
  {
    "product_id": "PROD-000010",
    "product_name": "Organic incremental moratorium Clothing",
    "category": "Clothing",
    "subcategory": "Clothing - Talk",
    "brand": "BookWorld",
    "base_price": 158.86,
    "description": "Radio six politics case skill prove discussion. Race wall its.\nFund interesting we effect few. These finish hit run theory modern couple. Art significant window professional.",
    "is_active": false,
    "last_updated": "2025-06-21T15:15:28.372023",
    "ingestion_time": "2025-06-21T15:15:28.372023"
  },
  {
    "product_id": "PROD-000011",
    "product_name": "Fundamental intangible hub Electronics",
    "category": "Electronics",
    "subcategory": "Electronics - Natural",
    "brand": "SportsPro",
    "base_price": 332.0,
    "description": "Laugh poor cell everybody time before individual. Run chance organization win fish. Voice discuss responsibility.\nDeep lawyer statement list. List stay building southern newspaper.",
    "is_active": false,
    "last_updated": "2025-06-21T15:15:28.372023",
    "ingestion_time": "2025-06-21T15:15:28.372023"
  },
  {
    "product_id": "PROD-000012",
    "product_name": "Self-enabling responsive protocol Books",
    "category": "Books",
    "subcategory": "Books - Information",
    "brand": "HomeComfort",
    "base_price": 723.63,
    "description": "Most black manage side let church. Safe want window else environment and. Poor present item market.",
    "is_active": false,
    "last_updated": "2025-06-21T15:15:28.372023",
    "ingestion_time": "2025-06-21T15:15:28.372023"
  },
  {
    "product_id": "PROD-000013",
    "product_name": "Adaptive local groupware Sports",
    "category": "Sports",
    "subcategory": "Sports - Tell",
    "brand": "TechCorp",
    "base_price": 668.58,
    "description": "Run skill ago difficult image cold. Gas find collection war summer.\nCan take join. World together weight them day accept prepare.",
    "is_active": false,
    "last_updated": "2025-06-21T15:15:28.372023",
    "ingestion_time": "2025-06-21T15:15:28.372023"
  },
  {
    "product_id": "PROD-000014",
    "product_name": "Total neutral instruction set Electronics",
    "category": "Electronics",
    "subcategory": "Electronics - Poor",
    "brand": "SportsPro",
    "base_price": 97.94,
    "description": "Practice night body whole small. Southern Mrs camera will grow yet.\nThe standard pretty positive. Ready southern turn actually per again. Nation human meet trouble bar statement.",
    "is_active": true,
    "last_updated": "2025-06-21T15:15:28.372023",
    "ingestion_time": "2025-06-21T15:15:28.372023"
  },
  {
    "product_id": "PROD-000015",
    "product_name": "Focused radical monitoring Sports",
    "category": "Sports",
    "subcategory": "Sports - Military",
    "brand": "HomeComfort",
    "base_price": 982.17,
    "description": "Fast yeah teach important. Begin wear religious pick. Final especially officer line sea policy.\nSay field detail similar. Single serve himself what loss. Five feel wife goal find.",
    "is_active": false,
    "last_updated": "2025-06-21T15:15:28.372023",
    "ingestion_time": "2025-06-21T15:15:28.372023"
  },
  {
    "product_id": "PROD-000016",
    "product_name": "Decentralized impactful utilization Clothing",
    "category": "Clothing",
    "subcategory": "Clothing - Some",
    "brand": "BookWorld",
    "base_price": 636.21,
    "description": "Nation management across institution woman. Understand eat voice. Responsibility term smile top.\nEdge between around a capital ever. My bad brother answer herself.",
    "is_active": true,
    "last_updated": "2025-06-21T15:15:28.372023",
    "ingestion_time": "2025-06-21T15:15:28.372023"
  },
  {
    "product_id": "PROD-000017",
    "product_name": "Seamless grid-enabled knowledge user Home & Garden",
    "category": "Home & Garden",
    "subcategory": "Home & Garden - Kind",
    "brand": "TechCorp",
    "base_price": 648.74,
    "description": "Impact either traditional prevent. Respond claim style whether cold suggest watch stuff. Age total surface news individual though court.",
    "is_active": true,
    "last_updated": "2025-06-21T15:15:28.372023",
    "ingestion_time": "2025-06-21T15:15:28.372023"
  },
  {
    "product_id": "PROD-000018",
    "product_name": "Proactive didactic implementation Electronics",
    "category": "Electronics",
    "subcategory": "Electronics - Including",
    "brand": "BookWorld",
    "base_price": 474.95,
    "description": "Democratic art risk person. Realize difficult something election environmental. Although another free east staff.",
    "is_active": true,
    "last_updated": "2025-06-21T15:15:28.372023",
    "ingestion_time": "2025-06-21T15:15:28.372023"
  },
  {
    "product_id": "PROD-000019",
    "product_name": "Seamless needs-based alliance Home & Garden",
    "category": "Home & Garden",
    "subcategory": "Home & Garden - Forget",
    "brand": "HomeComfort",
    "base_price": 943.64,
    "description": "Catch pick camera behavior. Use performance for herself.\nAfter follow recent machine white. Movie none family everything watch international. Second will need television different.",
    "is_active": true,
    "last_updated": "2025-06-21T15:15:28.372023",
    "ingestion_time": "2025-06-21T15:15:28.372023"
  },
  {
    "product_id": "PROD-000020",
    "product_name": "Organized logistical structure Home & Garden",
    "category": "Home & Garden",
    "subcategory": "Home & Garden - Bank",
    "brand": "BookWorld",
    "base_price": 838.98,
    "description": "Treatment machine brother push responsibility. Very avoid main to. Thing traditional seem. Seat study win another huge.\nLater within according Congress group spring. Ready her current son.",
    "is_active": false,
    "last_updated": "2025-06-21T15:15:28.372023",
    "ingestion_time": "2025-06-21T15:15:28.372023"
  },
  {
    "product_id": "PROD-000021",
    "product_name": "Customer-focused mobile extranet Clothing",
    "category": "Clothing",
    "subcategory": "Clothing - Up",
    "brand": "SportsPro",
    "base_price": 921.0,
    "description": "Investment lot trial recently general reveal. Control indeed quality leave billion population identify. Budget common church your.",
    "is_active": true,
    "last_updated": "2025-06-21T15:15:28.372023",
    "ingestion_time": "2025-06-21T15:15:28.372023"
  },
  {
    "product_id": "PROD-000022",
    "product_name": "Synchronized client-driven adapter Books",
    "category": "Books",
    "subcategory": "Books - Enough",
    "brand": "HomeComfort",
    "base_price": 110.47,
    "description": "Cold hand usually western. Mother school health finally. Modern investment to however. Responsibility long benefit create boy prepare black.",
    "is_active": false,
    "last_updated": "2025-06-21T15:15:28.372023",
    "ingestion_time": "2025-06-21T15:15:28.372023"
  },
  {
    "product_id": "PROD-000023",
    "product_name": "Centralized non-volatile algorithm Home & Garden",
    "category": "Home & Garden",
    "subcategory": "Home & Garden - They",
    "brand": "TechCorp",
    "base_price": 894.44,
    "description": "Determine hotel half through central of already. Too fact identify personal.\nBefore center whether group morning president.\nListen budget total space. Energy believe price west still shake.",
    "is_active": true,
    "last_updated": "2025-06-21T15:15:28.372023",
    "ingestion_time": "2025-06-21T15:15:28.372023"
  },
  {
    "product_id": "PROD-000024",
    "product_name": "Customizable didactic alliance Home & Garden",
    "category": "Home & Garden",
    "subcategory": "Home & Garden - Pressure",
    "brand": "TechCorp",
    "base_price": 385.66,
    "description": "Tend me local science term sense others. Power throughout center particularly field.\nRecord here eye possible kind. Decade might what a. Add member million perform.",
    "is_active": true,
    "last_updated": "2025-06-21T15:15:28.372023",
    "ingestion_time": "2025-06-21T15:15:28.372023"
  },
  {
    "product_id": "PROD-000025",
    "product_name": "Grass-roots 5thgeneration adapter Sports",
    "category": "Sports",
    "subcategory": "Sports - Sit",
    "brand": "StyleMax",
    "base_price": 131.88,
    "description": "Report our treatment. Investment ready north meeting result. Spring rich floor find center task discussion.",
    "is_active": false,
    "last_updated": "2025-06-21T15:15:28.372023",
    "ingestion_time": "2025-06-21T15:15:28.372023"
  },
  {
    "product_id": "PROD-000026",
    "product_name": "Customer-focused 5thgeneration data-warehouse Sports",
    "category": "Sports",
    "subcategory": "Sports - Imagine",
    "brand": "BookWorld",
    "base_price": 880.77,
    "description": "How week possible church meet degree relate.\nFrom take stock stuff star good own. Land avoid subject sing soldier. Mention none side season age rock.",
    "is_active": true,
    "last_updated": "2025-06-21T15:15:28.372023",
    "ingestion_time": "2025-06-21T15:15:28.372023"
  },
  {
    "product_id": "PROD-000027",
    "product_name": "Synergized fault-tolerant service-desk Home & Garden",
    "category": "Home & Garden",
    "subcategory": "Home & Garden - Act",
    "brand": "BookWorld",
    "base_price": 270.78,
    "description": "Determine experience anything actually throw once world.\nAcross hard business worker hundred example ball. Approach address enough important.",
    "is_active": false,
    "last_updated": "2025-06-21T15:15:28.372023",
    "ingestion_time": "2025-06-21T15:15:28.372023"
  },
  {
    "product_id": "PROD-000028",
    "product_name": "De-engineered 3rdgeneration infrastructure Electronics",
    "category": "Electronics",
    "subcategory": "Electronics - Who",
    "brand": "TechCorp",
    "base_price": 999.74,
    "description": "World produce he last training join black. Charge nation myself how produce how. Allow industry man value.\nImagine final series standard and system move. Win across lay. Trip sing carry idea father.",
    "is_active": true,
    "last_updated": "2025-06-21T15:15:28.372023",
    "ingestion_time": "2025-06-21T15:15:28.372023"
  },
  {
    "product_id": "PROD-000029",
    "product_name": "Virtual background frame Electronics",
    "category": "Electronics",
    "subcategory": "Electronics - Second",
    "brand": "StyleMax",
    "base_price": 962.01,
    "description": "Stay such when local after must everyone. Local sure experience traditional type. Explain financial red live decision drug eat full. Suffer whose bed mother from month financial.",
    "is_active": false,
    "last_updated": "2025-06-21T15:15:28.372023",
    "ingestion_time": "2025-06-21T15:15:28.372023"
  },
  {
    "product_id": "PROD-000030",
    "product_name": "Profound full-range framework Sports",
    "category": "Sports",
    "subcategory": "Sports - Catch",
    "brand": "BookWorld",
    "base_price": 125.99,
    "description": "Vote thought pay her among budget. Learn environment without business. Situation see art into.\nRule shoulder alone set. Good bag reason change design.\nTeach effect behavior draw young.",
    "is_active": false,
    "last_updated": "2025-06-21T15:15:28.372023",
    "ingestion_time": "2025-06-21T15:15:28.372023"
  },
  {
    "product_id": "PROD-000031",
    "product_name": "Open-source background capacity Home & Garden",
    "category": "Home & Garden",
    "subcategory": "Home & Garden - Suffer",
    "brand": "SportsPro",
    "base_price": 328.75,
    "description": "Account day doctor source trade. Shoulder might whether financial value. Thing major family factor specific.",
    "is_active": true,
    "last_updated": "2025-06-21T15:15:28.372023",
    "ingestion_time": "2025-06-21T15:15:28.372023"
  },
  {
    "product_id": "PROD-000032",
    "product_name": "User-friendly client-driven frame Books",
    "category": "Books",
    "subcategory": "Books - Family",
    "brand": "TechCorp",
    "base_price": 327.66,
    "description": "American station way dog. Hand simply set two agency believe. Mind check capital forget.\nCarry player surface exist. Should oil condition lot suddenly cost food not.",
    "is_active": false,
    "last_updated": "2025-06-21T15:15:28.372023",
    "ingestion_time": "2025-06-21T15:15:28.372023"
  },
  {
    "product_id": "PROD-000033",
    "product_name": "Upgradable scalable projection Books",
    "category": "Books",
    "subcategory": "Books - Than",
    "brand": "TechCorp",
    "base_price": 362.05,
    "description": "Bill civil huge laugh lay. Eye can home involve so health across. Wait wish follow member this dinner.\nMovie treat easy.",
    "is_active": true,
    "last_updated": "2025-06-21T15:15:28.372023",
    "ingestion_time": "2025-06-21T15:15:28.372023"
  },
  {
    "product_id": "PROD-000034",
    "product_name": "Expanded upward-trending array Clothing",
    "category": "Clothing",
    "subcategory": "Clothing - Though",
    "brand": "TechCorp",
    "base_price": 600.71,
    "description": "Health yourself every check. Technology their someone send explain product. Smile social school blue.",
    "is_active": false,
    "last_updated": "2025-06-21T15:15:28.372023",
    "ingestion_time": "2025-06-21T15:15:28.372023"
  },
  {
    "product_id": "PROD-000035",
    "product_name": "Virtual impactful synergy Books",
    "category": "Books",
    "subcategory": "Books - You",
    "brand": "TechCorp",
    "base_price": 81.56,
    "description": "Imagine off maybe hand. Former similar form thousand election best.",
    "is_active": true,
    "last_updated": "2025-06-21T15:15:28.372023",
    "ingestion_time": "2025-06-21T15:15:28.372023"
  },
  {
    "product_id": "PROD-000036",
    "product_name": "Focused composite intranet Clothing",
    "category": "Clothing",
    "subcategory": "Clothing - Least",
    "brand": "StyleMax",
    "base_price": 612.44,
    "description": "Ago send author different between. Call remain something. Top money point ever remain local.\nSomething during think red affect party.",
    "is_active": true,
    "last_updated": "2025-06-21T15:15:28.372023",
    "ingestion_time": "2025-06-21T15:15:28.372023"
  },
  {
    "product_id": "PROD-000037",
    "product_name": "Right-sized zero tolerance methodology Home & Garden",
    "category": "Home & Garden",
    "subcategory": "Home & Garden - Republican",
    "brand": "TechCorp",
    "base_price": 573.74,
    "description": "Economy despite night week none last.\nList citizen memory glass audience. Director game yeah money point reason program.\nTerm item cause city.",
    "is_active": true,
    "last_updated": "2025-06-21T15:15:28.372023",
    "ingestion_time": "2025-06-21T15:15:28.372023"
  },
  {
    "product_id": "PROD-000038",
    "product_name": "Function-based regional application Clothing",
    "category": "Clothing",
    "subcategory": "Clothing - Pretty",
    "brand": "SportsPro",
    "base_price": 133.31,
    "description": "Plan TV federal site.\nMother sea man. Body direction ago security how thousand treatment. Your night bag reason.",
    "is_active": true,
    "last_updated": "2025-06-21T15:15:28.372023",
    "ingestion_time": "2025-06-21T15:15:28.372023"
  },
  {
    "product_id": "PROD-000039",
    "product_name": "Cross-platform heuristic strategy Electronics",
    "category": "Electronics",
    "subcategory": "Electronics - Western",
    "brand": "StyleMax",
    "base_price": 522.0,
    "description": "Day step and education and maintain. Tend film move move whole field hair. Present media bring business reality understand.\nFactor hospital fine force body. Man according hair discussion risk.",
    "is_active": true,
    "last_updated": "2025-06-21T15:15:28.372023",
    "ingestion_time": "2025-06-21T15:15:28.372023"
  },
  {
    "product_id": "PROD-000040",
    "product_name": "Stand-alone zero tolerance Graphical User Interface Clothing",
    "category": "Clothing",
    "subcategory": "Clothing - Reach",
    "brand": "SportsPro",
    "base_price": 200.74,
    "description": "Meet nothing race few. While or prepare across. Not sit fill.\nFirm they worker at under later authority. Support manage figure budget. Act suddenly learn modern him season.",
    "is_active": true,
    "last_updated": "2025-06-21T15:15:28.372023",
    "ingestion_time": "2025-06-21T15:15:28.372023"
  },
  {
    "product_id": "PROD-000041",
    "product_name": "Grass-roots holistic initiative Home & Garden",
    "category": "Home & Garden",
    "subcategory": "Home & Garden - Official",
    "brand": "BookWorld",
    "base_price": 54.3,
    "description": "Least method activity. Possible coach interesting recently. Put book allow me may.",
    "is_active": false,
    "last_updated": "2025-06-21T15:15:28.372023",
    "ingestion_time": "2025-06-21T15:15:28.372023"
  },
  {
    "product_id": "PROD-000042",
    "product_name": "Team-oriented bottom-line forecast Sports",
    "category": "Sports",
    "subcategory": "Sports - House",
    "brand": "HomeComfort",
    "base_price": 100.7,
    "description": "Bad generation film reflect certainly rich. Whose billion race lot couple letter little pressure.\nAdmit range raise pay safe season last. Trade room recognize chance risk.",
    "is_active": true,
    "last_updated": "2025-06-21T15:15:28.372023",
    "ingestion_time": "2025-06-21T15:15:28.372023"
  },
  {
    "product_id": "PROD-000043",
    "product_name": "Team-oriented content-based Graphical User Interface Clothing",
    "category": "Clothing",
    "subcategory": "Clothing - National",
    "brand": "StyleMax",
    "base_price": 279.09,
    "description": "Traditional certainly most end white center join. Memory and growth beautiful like group.\nTogether often fast likely affect kind. Store foreign word foot.",
    "is_active": true,
    "last_updated": "2025-06-21T15:15:28.372023",
    "ingestion_time": "2025-06-21T15:15:28.372023"
  },
  {
    "product_id": "PROD-000044",
    "product_name": "Stand-alone solution-oriented access Sports",
    "category": "Sports",
    "subcategory": "Sports - History",
    "brand": "BookWorld",
    "base_price": 629.75,
    "description": "Population our unit trial. Teacher different bed first.\nHappy occur why you top only. Listen song that change.\nWorry let middle above note. Kid Congress book.",
    "is_active": true,
    "last_updated": "2025-06-21T15:15:28.372023",
    "ingestion_time": "2025-06-21T15:15:28.372023"
  },
  {
    "product_id": "PROD-000045",
    "product_name": "Reverse-engineered scalable circuit Home & Garden",
    "category": "Home & Garden",
    "subcategory": "Home & Garden - Arm",
    "brand": "BookWorld",
    "base_price": 406.76,
    "description": "Important campaign realize relate arrive buy available. Answer radio start believe organization bring compare.\nPolitical enough chance answer explain best remain. Task fear detail.",
    "is_active": true,
    "last_updated": "2025-06-21T15:15:28.372023",
    "ingestion_time": "2025-06-21T15:15:28.372023"
  },
  {
    "product_id": "PROD-000046",
    "product_name": "Inverse motivating focus group Sports",
    "category": "Sports",
    "subcategory": "Sports - Line",
    "brand": "BookWorld",
    "base_price": 338.07,
    "description": "Heavy although discuss theory hour usually year. Poor financial which newspaper cost dark energy. South development modern attack cost fly Mrs.",
    "is_active": true,
    "last_updated": "2025-06-21T15:15:28.372023",
    "ingestion_time": "2025-06-21T15:15:28.372023"
  },
  {
    "product_id": "PROD-000047",
    "product_name": "Secured impactful middleware Books",
    "category": "Books",
    "subcategory": "Books - More",
    "brand": "BookWorld",
    "base_price": 62.68,
    "description": "Sure floor bag stop life. I without skin stage page account.\nSignificant race see adult phone apply meeting.\nKnowledge serve task. Rise interest later expert data line.",
    "is_active": true,
    "last_updated": "2025-06-21T15:15:28.372023",
    "ingestion_time": "2025-06-21T15:15:28.372023"
  },
  {
    "product_id": "PROD-000048",
    "product_name": "Compatible zero-defect pricing structure Clothing",
    "category": "Clothing",
    "subcategory": "Clothing - Tax",
    "brand": "HomeComfort",
    "base_price": 744.53,
    "description": "Structure fear modern tonight painting wide address. Audience story wall remember live.\nPhone term court book pressure positive success point. No involve none effect.",
    "is_active": true,
    "last_updated": "2025-06-21T15:15:28.372023",
    "ingestion_time": "2025-06-21T15:15:28.372023"
  },
  {
    "product_id": "PROD-000049",
    "product_name": "Grass-roots methodical infrastructure Clothing",
    "category": "Clothing",
    "subcategory": "Clothing - Research",
    "brand": "SportsPro",
    "base_price": 570.77,
    "description": "Later smile what teach nice. Major oil structure inside. Relationship perform contain anything bed quickly new.\nAct order attention whose. Thought real word point order.",
    "is_active": false,
    "last_updated": "2025-06-21T15:15:28.372023",
    "ingestion_time": "2025-06-21T15:15:28.372023"
  }
]